cadmesh/__init__.py
cadmesh/OCCUtils/Common.py
cadmesh/OCCUtils/Construct.py
cadmesh/OCCUtils/Image.py
cadmesh/OCCUtils/Iteration.py
cadmesh/OCCUtils/Topology.py
cadmesh/OCCUtils/__init__.py
cadmesh/OCCUtils/base.py
cadmesh/OCCUtils/edge.py
cadmesh/OCCUtils/face.py
cadmesh/OCCUtils/shell.py
cadmesh/OCCUtils/solid.py
cadmesh/OCCUtils/types_lut.py
cadmesh/OCCUtils/vertex.py
cadmesh/OCCUtils/wire.py
cadmesh-0.2.3.dist-info/LICENSE
cadmesh-0.2.3.dist-info/METADATA
cadmesh-0.2.3.dist-info/WHEEL
cadmesh-0.2.3.dist-info/top_level.txt
cadmesh-0.2.3.dist-info/RECORD
