Metadata-Version: 2.1
Name: cadmesh
Version: 0.2.3
Summary: Meshing CAD files
Home-page: https://github.com/skoch9/cadmesh/
Author: Sebastian Koch
Author-email: 
License: UNKNOWN
Platform: UNKNOWN
Classifier: Programming Language :: Python :: 3
Classifier: License :: OSI Approved :: GNU General Public License v3 (GPLv3)
Classifier: Operating System :: OS Independent
